unit_sdk/__init__.py
unit_sdk/_version.py
unit_sdk/client.py
unit_sdk-1.2.13.dist-info/METADATA
unit_sdk-1.2.13.dist-info/WHEEL
unit_sdk-1.2.13.dist-info/licenses/LICENSE
unit_sdk-1.2.13.dist-info/RECORD
