Metadata-Version: 2.4
Name: unit-sdk
Version: 1.2.13
Summary: SDK for developing Unit Apps.
Author-email: "Steve G." <steve@pagekey.io>
License: Copyright 2025 PageKey Solutions, LLC
License-File: LICENSE
Requires-Python: >=3.12
Requires-Dist: pydantic
Requires-Dist: requests
